prodia/__init__.py
prodia/data.py
prodia/main.py
prodia_python-2.3.dist-info/LICENSE
prodia_python-2.3.dist-info/METADATA
prodia_python-2.3.dist-info/WHEEL
prodia_python-2.3.dist-info/top_level.txt
prodia_python-2.3.dist-info/RECORD
